ThreadingWrapper/__init__.py
ThreadingWrapper/concurrency.py
ThreadingWrapper/decorators.py
ThreadingWrapper/models.py
ThreadingWrapper-0.1.0.dist-info/LICENSE
ThreadingWrapper-0.1.0.dist-info/METADATA
ThreadingWrapper-0.1.0.dist-info/WHEEL
ThreadingWrapper-0.1.0.dist-info/top_level.txt
ThreadingWrapper-0.1.0.dist-info/RECORD
