Metadata-Version: 2.1
Name: ThreadingWrapper
Version: 0.1.0
Summary: A threading wrapper which can be used quickly to run tasks in parallel
Home-page: https://github.com/thedly/pythreading-wrapper
Author: Tejas Hedly
Author-email: tejas.hedly@gmail.com
License: GNU GENERAL PUBLIC LICENSE
Classifier: License :: OSI Approved :: GNU Lesser General Public License v3 (LGPLv3)
Classifier: Operating System :: OS Independent
Classifier: Programming Language :: Python :: 3.6
Classifier: Programming Language :: Python :: 3.7
Classifier: Programming Language :: Python :: 3.8
Classifier: Programming Language :: Python :: 3.9
Requires-Python: >=3.6
License-File: LICENSE
